rtl/regfile.sv
`timescale 1ns/1ps
module regfile #(
  parameter XLEN = 32,
  parameter REG_COUNT = 32
)(
  input              clk,
  input              rst,
  input              we,
  input  [4:0]       rs1,
  input  [4:0]       rs2,
  input  [4:0]       rd,
  input  [XLEN-1:0]  wd,
  output [XLEN-1:0]  rd1,
  output [XLEN-1:0]  rd2,

  input  [4:0]       dbg_addr,
  output [XLEN-1:0]  dbg_data
);

  reg [XLEN-1:0] regs [0:REG_COUNT-1];
  integer i;

  // Write on NEGEDGE to avoid same-edge race with core's wb signals (Icarus-stable)
  always @(negedge clk) begin
    if (rst) begin
      for (i = 0; i < REG_COUNT; i = i + 1)
        regs[i] <= 0;
    end else begin
      if (we && rd != 0)
        regs[rd] <= wd;
    end
  end

  // Combinational reads
  assign rd1 = (rs1 == 0) ? 0 : regs[rs1];
  assign rd2 = (rs2 == 0) ? 0 : regs[rs2];

  assign dbg_data = (dbg_addr == 0) ? 0 : regs[dbg_addr];

endmodule

rtl/core_pipe5.sv
`timescale 1ns/1ps
// RV32I 5-stage pipeline
// IF -> ID -> EX -> MEM -> WB
// Includes forwarding + load-use hazard stall

module core_pipe5 #(
  parameter XLEN = 32,
  parameter IMEM_WORDS = 64,
  parameter IMEM_HEX   = "build/padded.hex",
  parameter DMEM_WORDS = 64
)(
  input  wire clk,
  input  wire rst,
  output reg  [XLEN-1:0] pc,
  output reg  illegal_insn,
  output wire [XLEN-1:0] dbg_x10
);

reg [31:0] imem [0:IMEM_WORDS-1];
reg [31:0] dmem [0:DMEM_WORDS-1];

integer i;

localparam NOP = 32'h00000013;

initial begin
  for(i=0;i<IMEM_WORDS;i=i+1) imem[i]=NOP;
  for(i=0;i<DMEM_WORDS;i=i+1) dmem[i]=0;
  $readmemh(IMEM_HEX,imem);
end

wire [31:0] instr_f = imem[pc[($clog2(IMEM_WORDS)+1):2]];

reg [31:0] ifid_pc;
reg [31:0] ifid_instr;

wire [6:0] op_d  = ifid_instr[6:0];
wire [4:0] rd_d  = ifid_instr[11:7];
wire [2:0] f3_d  = ifid_instr[14:12];
wire [4:0] rs1_d = ifid_instr[19:15];
wire [4:0] rs2_d = ifid_instr[24:20];
wire [6:0] f7_d  = ifid_instr[31:25];

wire [31:0] imm_i_d = {{20{ifid_instr[31]}},ifid_instr[31:20]};
wire [31:0] imm_s_d = {{20{ifid_instr[31]}},ifid_instr[31:25],ifid_instr[11:7]};
wire [31:0] imm_b_d = {{19{ifid_instr[31]}},ifid_instr[31],ifid_instr[7],ifid_instr[30:25],ifid_instr[11:8],1'b0};
wire [31:0] imm_j_d = {{11{ifid_instr[31]}},ifid_instr[31],ifid_instr[19:12],ifid_instr[20],ifid_instr[30:21],1'b0};

wire [31:0] rf_rd1, rf_rd2;

reg wb_we;
reg [4:0] wb_rd;
reg [31:0] wb_wd;

regfile u_rf(
.clk(clk),
.rst(rst),
.we(wb_we),
.rs1(rs1_d),
.rs2(rs2_d),
.rd(wb_rd),
.wd(wb_wd),
.rd1(rf_rd1),
.rd2(rf_rd2),
.dbg_addr(5'd10),
.dbg_data(dbg_x10)
);

reg [31:0] idex_pc;
reg [31:0] idex_rs1_val;
reg [31:0] idex_rs2_val;
reg [31:0] idex_imm;
reg [4:0] idex_rd;
reg [4:0] idex_rs1;
reg [4:0] idex_rs2;
reg [2:0] idex_f3;

reg idex_regwrite;
reg idex_is_load;
reg idex_is_store;
reg idex_is_branch;
reg idex_is_jal;
reg idex_alu_imm;

reg [3:0] idex_alu_op;

localparam ALU_ADD=0;
localparam ALU_SUB=1;

function [31:0] alu_fn;
input [3:0] op;
input [31:0] a;
input [31:0] b;
begin
case(op)
ALU_ADD: alu_fn=a+b;
ALU_SUB: alu_fn=a-b;
default: alu_fn=0;
endcase
end
endfunction

reg [31:0] exmem_alu;
reg [31:0] exmem_store_data;
reg [31:0] exmem_wb_data;
reg [4:0] exmem_rd;
reg exmem_regwrite;
reg exmem_is_load;
reg exmem_is_store;

wire [31:0] dmem_rdata=dmem[exmem_alu[($clog2(DMEM_WORDS)+1):2]];

reg [31:0] memwb_wdata;
reg [4:0] memwb_rd;
reg memwb_we;

wire id_uses_rs2 =
(op_d==7'b0110011)||
(op_d==7'b0100011)||
(op_d==7'b1100011);

wire load_use_hazard=
idex_is_load &&
(idex_rd!=0) &&
((idex_rd==rs1_d) || (id_uses_rs2 && idex_rd==rs2_d));

reg [31:0] ex_rs1_fwd;
reg [31:0] ex_rs2_fwd;

always @(*) begin
ex_rs1_fwd=idex_rs1_val;
ex_rs2_fwd=idex_rs2_val;

if(exmem_regwrite && exmem_rd!=0 && exmem_rd==idex_rs1)
ex_rs1_fwd=exmem_alu;

if(exmem_regwrite && exmem_rd!=0 && exmem_rd==idex_rs2)
ex_rs2_fwd=exmem_alu;

if(memwb_we && memwb_rd!=0 && memwb_rd==idex_rs1)
ex_rs1_fwd=memwb_wdata;

if(memwb_we && memwb_rd!=0 && memwb_rd==idex_rs2)
ex_rs2_fwd=memwb_wdata;
end

wire [31:0] ex_a=ex_rs1_fwd;
wire [31:0] ex_b=idex_alu_imm?idex_imm:ex_rs2_fwd;
wire [31:0] ex_alu=alu_fn(idex_alu_op,ex_a,ex_b);

wire ex_beq=(ex_rs1_fwd==ex_rs2_fwd);
wire ex_take_branch=idex_is_branch && ex_beq;

wire [31:0] ex_branch_tgt=idex_pc+idex_imm;
wire [31:0] ex_jal_tgt=idex_pc+idex_imm;
wire [31:0] ex_pc_plus4=idex_pc+4;

reg flush_ifid;
reg [31:0] pc_next;

always @(*) begin
flush_ifid=0;
pc_next=pc+4;

if(ex_take_branch) begin
pc_next=ex_branch_tgt;
flush_ifid=1;
end

if(idex_is_jal) begin
pc_next=ex_jal_tgt;
flush_ifid=1;
end
end

always @(posedge clk) begin
if(rst) begin
pc<=0;
ifid_instr<=NOP;
ifid_pc<=0;
end
else begin

wb_we<=memwb_we;
wb_rd<=memwb_rd;
wb_wd<=memwb_wdata;

if(exmem_is_store)
dmem[exmem_alu[($clog2(DMEM_WORDS)+1):2]]<=exmem_store_data;

memwb_wdata <= (exmem_is_load) ? dmem_rdata : exmem_wb_data;
memwb_rd<=exmem_rd;
memwb_we<=exmem_regwrite;

exmem_alu<=ex_alu;
exmem_store_data<=ex_rs2_fwd;
exmem_rd<=idex_rd;
exmem_regwrite<=idex_regwrite;
exmem_is_load<=idex_is_load;
exmem_is_store<=idex_is_store;
exmem_wb_data<=idex_is_jal?ex_pc_plus4:ex_alu;

if(load_use_hazard) begin
idex_regwrite<=0;
idex_is_load<=0;
idex_is_store<=0;
idex_is_branch<=0;
idex_is_jal<=0;
end
else begin
idex_pc<=ifid_pc;
idex_rs1_val<=rf_rd1;
idex_rs2_val<=rf_rd2;
idex_rs1<=rs1_d;
idex_rs2<=rs2_d;
idex_rd<=rd_d;
idex_f3<=f3_d;

idex_regwrite<=0;
idex_is_load<=0;
idex_is_store<=0;
idex_is_branch<=0;
idex_is_jal<=0;
idex_alu_imm<=0;
idex_alu_op<=ALU_ADD;
idex_imm<=imm_i_d;

case(op_d)

7'b0110011: begin
idex_regwrite<=1;
end

7'b0010011: begin
idex_regwrite<=1;
idex_alu_imm<=1;
end

7'b0000011: begin
idex_regwrite<=1;
idex_is_load<=1;
idex_alu_imm<=1;
end

7'b0100011: begin
idex_is_store<=1;
idex_alu_imm<=1;
idex_imm<=imm_s_d;
end

7'b1100011: begin
idex_is_branch<=1;
idex_imm<=imm_b_d;
end

7'b1101111: begin
idex_regwrite<=1;
idex_is_jal<=1;
idex_imm<=imm_j_d;
end

default: illegal_insn<=1;

endcase

end

if(flush_ifid) begin
ifid_instr<=NOP;
pc<=pc_next;
end
else if(load_use_hazard) begin
pc<=pc;
ifid_instr<=ifid_instr;
end
else begin
ifid_pc<=pc;
ifid_instr<=instr_f;
pc<=pc_next;
end

end
end

endmodule

tb/tb_core_pipe5.sv
`timescale 1ns/1ps
module tb_core_pipe5;

  reg clk;
  reg rst;
  wire [31:0] pc;
  wire illegal;
  wire [31:0] x10;

  core_pipe5 #(
    .IMEM_WORDS(64),
    .IMEM_HEX("build/padded.hex")
  ) dut (
    .clk(clk),
    .rst(rst),
    .pc(pc),
    .illegal_insn(illegal),
    .dbg_x10(x10)
  );

  initial clk = 0;
  always #5 clk = ~clk;

  initial begin
    // ✅ ADD THESE TWO LINES HERE
    $dumpfile("build/wave_pipe_alu.vcd");
    $dumpvars(0, tb_core_pipe5);

    $display("SIM START (PIPE ALU)");
    rst = 1; #20 rst = 0;

    // Let pipeline fill/drain
    #300;

    if (illegal) $display("FAIL: illegal_insn=1");
    else if (x10 == 32'd12) $display("PASS: x10=%0d", x10);
    else $display("FAIL: x10=%0d expected 12", x10);

    $finish;
  end
endmodule

build/wave_pipe_alu.vcd
$date
	Fri Mar  6 21:30:49 2026
$end
$version
	Icarus Verilog
$end
$timescale
	1ps
$end
$scope module tb_core_pipe5 $end
$var wire 32 ! x10 [31:0] $end
$var wire 32 " pc [31:0] $end
$var wire 1 # illegal $end
$var reg 1 $ clk $end
$var reg 1 % rst $end
$scope module dut $end
$var wire 1 $ clk $end
$var wire 32 & dmem_rdata [31:0] $end
$var wire 32 ' ex_a [31:0] $end
$var wire 1 ( ex_take_branch $end
$var wire 1 ) id_uses_rs2 $end
$var wire 32 * instr_f [31:0] $end
$var wire 1 + load_use_hazard $end
$var wire 1 % rst $end
$var wire 5 , rs2_d [4:0] $end
$var wire 5 - rs1_d [4:0] $end
$var wire 32 . rf_rd2 [31:0] $end
$var wire 32 / rf_rd1 [31:0] $end
$var wire 5 0 rd_d [4:0] $end
$var wire 7 1 op_d [6:0] $end
$var wire 32 2 imm_s_d [31:0] $end
$var wire 32 3 imm_j_d [31:0] $end
$var wire 32 4 imm_i_d [31:0] $end
$var wire 32 5 imm_b_d [31:0] $end
$var wire 7 6 f7_d [6:0] $end
$var wire 3 7 f3_d [2:0] $end
$var wire 32 8 ex_pc_plus4 [31:0] $end
$var wire 32 9 ex_jal_tgt [31:0] $end
$var wire 32 : ex_branch_tgt [31:0] $end
$var wire 1 ; ex_beq $end
$var wire 32 < ex_b [31:0] $end
$var wire 32 = ex_alu [31:0] $end
$var wire 32 > dbg_x10 [31:0] $end
$var reg 32 ? ex_rs1_fwd [31:0] $end
$var reg 32 @ ex_rs2_fwd [31:0] $end
$var reg 32 A exmem_alu [31:0] $end
$var reg 1 B exmem_is_load $end
$var reg 1 C exmem_is_store $end
$var reg 5 D exmem_rd [4:0] $end
$var reg 1 E exmem_regwrite $end
$var reg 32 F exmem_store_data [31:0] $end
$var reg 32 G exmem_wb_data [31:0] $end
$var reg 1 H flush_ifid $end
$var reg 1 I idex_alu_imm $end
$var reg 4 J idex_alu_op [3:0] $end
$var reg 3 K idex_f3 [2:0] $end
$var reg 32 L idex_imm [31:0] $end
$var reg 1 M idex_is_branch $end
$var reg 1 N idex_is_jal $end
$var reg 1 O idex_is_load $end
$var reg 1 P idex_is_store $end
$var reg 32 Q idex_pc [31:0] $end
$var reg 5 R idex_rd [4:0] $end
$var reg 1 S idex_regwrite $end
$var reg 5 T idex_rs1 [4:0] $end
$var reg 32 U idex_rs1_val [31:0] $end
$var reg 5 V idex_rs2 [4:0] $end
$var reg 32 W idex_rs2_val [31:0] $end
$var reg 32 X ifid_instr [31:0] $end
$var reg 32 Y ifid_pc [31:0] $end
$var reg 1 # illegal_insn $end
$var reg 5 Z memwb_rd [4:0] $end
$var reg 32 [ memwb_wdata [31:0] $end
$var reg 1 \ memwb_we $end
$var reg 32 ] pc [31:0] $end
$var reg 32 ^ pc_next [31:0] $end
$var reg 5 _ wb_rd [4:0] $end
$var reg 32 ` wb_wd [31:0] $end
$var reg 1 a wb_we $end
$var integer 32 b i [31:0] $end
$scope function alu_fn $end
$var reg 32 c a [31:0] $end
$var reg 32 d b [31:0] $end
$var reg 4 e op [3:0] $end
$upscope $end
$scope module u_rf $end
$var wire 1 $ clk $end
$var wire 5 f dbg_addr [4:0] $end
$var wire 5 g rd [4:0] $end
$var wire 5 h rs1 [4:0] $end
$var wire 5 i rs2 [4:0] $end
$var wire 1 % rst $end
$var wire 32 j wd [31:0] $end
$var wire 1 a we $end
$var wire 32 k rd2 [31:0] $end
$var wire 32 l rd1 [31:0] $end
$var wire 32 m dbg_data [31:0] $end
$var integer 32 n i [31:0] $end
$upscope $end
$upscope $end
$upscope $end
$enddefinitions $end
#0
$dumpvars
b100000 n
b0 m
bx l
bx k
bx j
bx i
bx h
bx g
b1010 f
bx e
bx d
bx c
b1000000 b
xa
bx `
bx _
bx ^
bx ]
x\
bx [
bx Z
bx Y
bx X
bx W
bx V
bx U
bx T
xS
bx R
bx Q
xP
xO
xN
xM
bx L
bx K
bx J
xI
xH
bx G
bx F
xE
bx D
xC
xB
bx A
bx @
bx ?
b0 >
b0 =
bx <
x;
bx :
bx 9
bx 8
bx 7
bx 6
bx0 5
bx 4
bx0 3
bx 2
bx 1
bx 0
bx /
bx .
bx -
bx ,
x+
bx *
x)
x(
bx '
bx &
1%
0$
x#
bx "
b0 !
$end
#5000
0)
b0 /
b0 l
b0 .
b0 k
b10011 1
b0 0
b0 7
b0 -
b0 h
b0 ,
b0 i
b0 6
b0 4
b0 2
b0 5
b0 3
b100 ^
0H
b10100000000000010010011 *
b0 Y
b10011 X
b0 "
b0 ]
1$
#10000
b100000 n
0$
#15000
1$
#20000
0$
0%
#25000
0+
b10100000000000100010011 *
b1 0
b101 ,
b101 i
b101 4
b1 2
b100000000000 5
b100000000100 3
b0 d
b0 c
b0 e
b0 <
b1000 ^
0(
1;
b0 @
b0 '
b0 ?
b0 &
b100 "
b100 ]
b10100000000000010010011 X
b0 :
b0 9
b0 L
b0 J
1I
0N
0M
0P
0O
1S
b0 K
b0 R
b0 V
b0 T
b0 W
b0 U
b100 8
b0 Q
b0 A
1$
#30000
0$
#35000
b101 =
b101 d
b1000001000011001100011 *
b10 0
b10 2
b10 5
b1100 ^
b101 <
b1000 "
b1000 ]
b10100000000000100010011 X
b100 Y
b101 :
b101 9
b101 L
1I
1S
b1 R
b101 V
b0 G
0C
0B
1E
b0 D
b0 F
1$
#40000
0$
#45000
1)
b10011 *
b1100011 1
b1100 0
b1 -
b1 h
b10 ,
b10 i
b10 4
b1100 2
b1100 5
b1000000000000010 3
b10000 ^
b1100 "
b1100 ]
b1000001000011001100011 X
b1000 Y
1I
1S
b10 R
b1001 :
b1001 9
b1000 8
b100 Q
b101 G
b1 D
b101 A
1\
b0 Z
b0 [
1$
#50000
0$
#55000
0)
1H
b1010 =
b101 c
b110000000000010100010011 *
b10011 1
b0 0
b0 -
b0 h
b0 ,
b0 i
b0 4
b0 2
b0 5
b0 3
1(
b10100 ^
b101 '
b101 ?
1;
b101 @
b10000 "
b10000 ]
b10011 X
b1100 Y
1M
b1100 L
0I
0S
b1100 R
b10 V
b1 T
b10100 :
b10100 9
b1100 8
b1000 Q
b10 D
b1 Z
b101 [
b0 `
b0 j
b0 _
b0 g
1a
1$
#60000
0$
#65000
b0 =
b0 d
b0 c
b10011 *
b0 <
0(
b11000 ^
0H
b0 @
1;
b0 '
b0 ?
b10100 "
b10100 ]
1I
1S
b0 L
0M
b0 R
b0 V
b0 T
b1100 :
b1100 9
b10000 8
b1100 Q
b1010 G
0E
b1100 D
b101 F
b1010 A
b10 Z
b101 `
b101 j
b1 _
b1 g
1$
#70000
0$
#75000
b11100 ^
b11000 "
b11000 ]
b10100 Y
1I
1S
b0 G
1E
b0 D
b0 F
b0 A
0\
b1100 Z
b1010 [
b10 _
b10 g
1$
#80000
0$
#85000
b100000 ^
b11100 "
b11100 ]
b11000 Y
1I
1S
b10100 :
b10100 9
b11000 8
b10100 Q
1\
b0 Z
b0 [
b1010 `
b1010 j
b1100 _
b1100 g
0a
1$
#90000
0$
#95000
b100100 ^
b100000 "
b100000 ]
b11100 Y
1I
1S
b11000 :
b11000 9
b11100 8
b11000 Q
b0 `
b0 j
b0 _
b0 g
1a
1$
#100000
0$
#105000
b101000 ^
b100100 "
b100100 ]
b100000 Y
1I
1S
b11100 :
b11100 9
b100000 8
b11100 Q
1$
#110000
0$
#115000
b101100 ^
b101000 "
b101000 ]
b100100 Y
1I
1S
b100000 :
b100000 9
b100100 8
b100000 Q
1$
#120000
0$
#125000
b110000 ^
b101100 "
b101100 ]
b101000 Y
1I
1S
b100100 :
b100100 9
b101000 8
b100100 Q
1$
#130000
0$
#135000
b110100 ^
b110000 "
b110000 ]
b101100 Y
1I
1S
b101000 :
b101000 9
b101100 8
b101000 Q
1$
#140000
0$
#145000
b111000 ^
b110100 "
b110100 ]
b110000 Y
1I
1S
b101100 :
b101100 9
b110000 8
b101100 Q
1$
#150000
0$
#155000
b111100 ^
b111000 "
b111000 ]
b110100 Y
1I
1S
b110000 :
b110000 9
b110100 8
b110000 Q
1$
#160000
0$
#165000
b1000000 ^
b111100 "
b111100 ]
b111000 Y
1I
1S
b110100 :
b110100 9
b111000 8
b110100 Q
1$
#170000
0$
#175000
b1000100 ^
b1000000 "
b1000000 ]
b111100 Y
1I
1S
b111000 :
b111000 9
b111100 8
b111000 Q
1$
#180000
0$
#185000
b1001000 ^
b1000100 "
b1000100 ]
b1000000 Y
1I
1S
b111100 :
b111100 9
b1000000 8
b111100 Q
1$
#190000
0$
#195000
b1001100 ^
b1001000 "
b1001000 ]
b1000100 Y
1I
1S
b1000000 :
b1000000 9
b1000100 8
b1000000 Q
1$
#200000
0$
#205000
b1010000 ^
b1001100 "
b1001100 ]
b1001000 Y
1I
1S
b1000100 :
b1000100 9
b1001000 8
b1000100 Q
1$
#210000
0$
#215000
b1010100 ^
b1010000 "
b1010000 ]
b1001100 Y
1I
1S
b1001000 :
b1001000 9
b1001100 8
b1001000 Q
1$
#220000
0$
#225000
b1011000 ^
b1010100 "
b1010100 ]
b1010000 Y
1I
1S
b1001100 :
b1001100 9
b1010000 8
b1001100 Q
1$
#230000
0$
#235000
b1011100 ^
b1011000 "
b1011000 ]
b1010100 Y
1I
1S
b1010000 :
b1010000 9
b1010100 8
b1010000 Q
1$
#240000
0$
#245000
b1100000 ^
b1011100 "
b1011100 ]
b1011000 Y
1I
1S
b1010100 :
b1010100 9
b1011000 8
b1010100 Q
1$
#250000
0$
#255000
b1100100 ^
b1100000 "
b1100000 ]
b1011100 Y
1I
1S
b1011000 :
b1011000 9
b1011100 8
b1011000 Q
1$
#260000
0$
#265000
b1101000 ^
b1100100 "
b1100100 ]
b1100000 Y
1I
1S
b1011100 :
b1011100 9
b1100000 8
b1011100 Q
1$
#270000
0$
#275000
b1101100 ^
b1101000 "
b1101000 ]
b1100100 Y
1I
1S
b1100000 :
b1100000 9
b1100100 8
b1100000 Q
1$
#280000
0$
#285000
b1110000 ^
b1101100 "
b1101100 ]
b1101000 Y
1I
1S
b1100100 :
b1100100 9
b1101000 8
b1100100 Q
1$
#290000
0$
#295000
b1110100 ^
b1110000 "
b1110000 ]
b1101100 Y
1I
1S
b1101000 :
b1101000 9
b1101100 8
b1101000 Q
1$
#300000
0$
#305000
b1111000 ^
b1110100 "
b1110100 ]
b1110000 Y
1I
1S
b1101100 :
b1101100 9
b1110000 8
b1101100 Q
1$
#310000
0$
#315000
b1111100 ^
b1111000 "
b1111000 ]
b1110100 Y
1I
1S
b1110000 :
b1110000 9
b1110100 8
b1110000 Q
1$
